{
    "gpu23": {
        "snap_orkut": [
            412081, 
            359485, 
            295624, 
            230031, 
            168304, 
            113313, 
            69273, 
            36847, 
            15972
        ], 
        "snap_friendster": [
            "TLE", 
            "TLE", 
            "TLE", 
            4802936, 
            3253814, 
            2108492, 
            1264775, 
            678866, 
            324602
        ], 
        "webgraph_webbase": [
            1718552, 
            2216086, 
            2470455, 
            1946621, 
            1470504, 
            1069306, 
            892355, 
            702724, 
            513698
        ], 
        "webgraph_twitter": [
            "TLE", 
            "TLE", 
            5201903, 
            3502644, 
            2258930, 
            1350859, 
            723689, 
            326626, 
            109554
        ]
    }, 
    "knl": {
        "snap_orkut": [
            1431097, 
            1183182, 
            954589, 
            746580, 
            560391, 
            398248, 
            267034, 
            170102, 
            104011
        ], 
        "snap_friendster": [
            "TLE", 
            "TLE", 
            "TLE", 
            "TLE", 
            "TLE", 
            "TLE", 
            4710301, 
            2992744, 
            1974739
        ], 
        "webgraph_webbase": [
            "TLE", 
            "TLE", 
            "TLE", 
            "TLE", 
            4711384, 
            3522422, 
            2992750, 
            2372085, 
            1806441
        ], 
        "webgraph_twitter": [
            "TLE", 
            "TLE", 
            "TLE", 
            "TLE", 
            "TLE", 
            4347272, 
            2452650, 
            1254481, 
            592255
        ]
    }
}